biobit-0.0.9.dist-info/METADATA
biobit-0.0.9.dist-info/WHEEL
biobit/__init__.py
biobit/collections/__init__.py
biobit/collections/interval_tree/__init__.py
biobit/collections/interval_tree/__init__.pyi
biobit/collections/interval_tree/bits.pyi
biobit/collections/interval_tree/forest.py
biobit/collections/interval_tree/hits.pyi
biobit/collections/interval_tree/segments.pyi
biobit/collections/interval_tree/tests/test_bits.py
biobit/collections/interval_tree/tests/test_forest.py
biobit/collections/interval_tree/tests/test_hit_segments.py
biobit/collections/interval_tree/tests/test_hits.py
biobit/core/__init__.py
biobit/core/__init__.pyi
biobit/core/loc/__init__.py
biobit/core/loc/__init__.pyi
biobit/core/loc/chain_interval.pyi
biobit/core/loc/interval.pyi
biobit/core/loc/mapping/__init__.py
biobit/core/loc/mapping/__init__.pyi
biobit/core/loc/mapping/chain_map.pyi
biobit/core/loc/orientation.pyi
biobit/core/loc/per_orientation.pyi
biobit/core/loc/per_strand.pyi
biobit/core/loc/strand.pyi
biobit/core/loc/tests/test_chain_interval.py
biobit/core/loc/tests/test_chain_map.py
biobit/core/loc/tests/test_interval.py
biobit/core/loc/tests/test_orientation.py
biobit/core/loc/tests/test_per_orientation.py
biobit/core/loc/tests/test_per_strand.py
biobit/core/loc/tests/test_strand.py
biobit/core/ngs/__init__.py
biobit/core/ngs/__init__.pyi
biobit/core/ngs/layout.pyi
biobit/core/ngs/mates_orientation.pyi
biobit/core/ngs/strandedness.pyi
biobit/core/ngs/tests/test_layout.py
biobit/core/ngs/tests/test_mates_orientation.py
biobit/core/ngs/tests/test_strandedness.py
biobit/io/__init__.py
biobit/io/bam/__init__.py
biobit/io/bam/__init__.pyi
biobit/io/bam/reader.pyi
biobit/io/bam/test_bam.py
biobit/io/bed/__init__.py
biobit/io/bed/__init__.pyi
biobit/io/bed/test_bed.py
biobit/io/fasta/__init__.py
biobit/io/fasta/__init__.pyi
biobit/io/fasta/test_fasta.py
biobit/io/protocols.py
biobit/py.typed
biobit/rs.cpython-313t-x86_64-linux-gnu.so
biobit/test_utils.py
biobit/toolkit/__init__.py
biobit/toolkit/annotome/__init__.py
biobit-0.0.9.dist-info/RECORD
