Metadata-Version: 2.4
Name: biobit
Version: 0.0.9
Classifier: Programming Language :: Rust
Classifier: Programming Language :: Python :: 3
Classifier: Programming Language :: Python :: Implementation :: CPython
Classifier: License :: OSI Approved :: MIT License
Requires-Dist: attrs==25.3.0
Requires-Dist: cattrs[pyyaml]==25.2.0
Requires-Dist: pyyaml==6.0.2
Summary: Rust-powered Python library for biological data analysis
Home-Page: https://github.com/biomancy/biobit
Author: Aleksandr Fedorov
License: MIT
Requires-Python: >=3.13
Project-URL: Source Code, https://github.com/biomancy/biobit
